[
  {
    "id": "n1",
    "start": 0.0,
    "end": 1.67
  },
  {
    "id": "n2",
    "start": 2.07,
    "end": 27.2
  },
  {
    "id": "n3",
    "start": 27.6,
    "end": 42.6
  },
  {
    "id": "n4",
    "start": 43.0,
    "end": 44.62
  },
  {
    "id": "n5",
    "start": 45.02,
    "end": 46.09
  },
  {
    "id": "n6",
    "start": 46.49,
    "end": 71.66
  },
  {
    "id": "n7",
    "start": 72.06,
    "end": 74.34
  },
  {
    "id": "n8",
    "start": 74.74,
    "end": 98.84
  },
  {
    "id": "n9",
    "start": 99.24,
    "end": 128.91
  },
  {
    "id": "n10",
    "start": 129.31,
    "end": 154.34
  },
  {
    "id": "n11",
    "start": 154.74,
    "end": 167.33
  },
  {
    "id": "n12",
    "start": 167.73,
    "end": 170.65
  },
  {
    "id": "n13",
    "start": 171.05,
    "end": 193.07
  },
  {
    "id": "n14",
    "start": 193.47,
    "end": 209.86
  },
  {
    "id": "n15",
    "start": 210.26,
    "end": 212.68
  },
  {
    "id": "n16",
    "start": 213.08,
    "end": 215.68
  },
  {
    "id": "n17",
    "start": 216.08,
    "end": 248.63
  },
  {
    "id": "n18",
    "start": 249.03,
    "end": 260.73
  },
  {
    "id": "n19",
    "start": 261.13,
    "end": 280.17
  },
  {
    "id": "n20",
    "start": 280.57,
    "end": 295.71
  },
  {
    "id": "n21",
    "start": 296.11,
    "end": 298.25
  },
  {
    "id": "n22",
    "start": 298.65,
    "end": 319.32
  },
  {
    "id": "n23",
    "start": 319.72,
    "end": 397.04
  },
  {
    "id": "n24",
    "start": 397.44,
    "end": 399.76
  },
  {
    "id": "n25",
    "start": 400.16,
    "end": 415.25
  },
  {
    "id": "n26",
    "start": 415.65,
    "end": 417.37
  },
  {
    "id": "n27",
    "start": 417.77,
    "end": 445.4
  },
  {
    "id": "n28",
    "start": 445.8,
    "end": 465.86
  },
  {
    "id": "n29",
    "start": 466.26,
    "end": 467.98
  },
  {
    "id": "n30",
    "start": 468.38,
    "end": 490.63
  },
  {
    "id": "n31",
    "start": 491.03,
    "end": 493.02
  },
  {
    "id": "n32",
    "start": 493.42,
    "end": 515.86
  },
  {
    "id": "n33",
    "start": 516.26,
    "end": 534.27
  },
  {
    "id": "n34",
    "start": 534.67,
    "end": 582.37
  }
]